friar/__init__.py
friar-0.0.11.dist-info/DESCRIPTION.rst
friar-0.0.11.dist-info/METADATA
friar-0.0.11.dist-info/RECORD
friar-0.0.11.dist-info/WHEEL
friar-0.0.11.dist-info/metadata.json
friar-0.0.11.dist-info/top_level.txt
