Metadata-Version: 2.0
Name: friar
Version: 0.0.11
Summary: A simple Python wrapper for jsonrpc interfaces
Home-page: http://jameselford.com/friar
Author: James Elford
Author-email: james.p.elford@gmail.com
License: MIT
Keywords: jsonrpc,client
Platform: UNKNOWN
Classifier: Development Status :: 3 - Alpha
Classifier: Intended Audience :: Developers
Classifier: Programming Language :: Python :: 3.4
Requires-Dist: requests
